MANIFEST.in
README.txt
setup.cfg
setup.py
docs/HISTORY.txt
docs/INSTALL.txt
docs/LICENSE.GPL
docs/LICENSE.txt
ityou/__init__.py
ityou.follow.egg-info/PKG-INFO
ityou.follow.egg-info/SOURCES.txt
ityou.follow.egg-info/dependency_links.txt
ityou.follow.egg-info/entry_points.txt
ityou.follow.egg-info/namespace_packages.txt
ityou.follow.egg-info/not-zip-safe
ityou.follow.egg-info/paster_plugins.txt
ityou.follow.egg-info/requires.txt
ityou.follow.egg-info/top_level.txt
ityou/follow/__init__.py
ityou/follow/config.py
ityou/follow/configure.zcml
ityou/follow/dbapi.py
ityou/follow/interfaces.py
ityou/follow/tests.py
ityou/follow/translate.sh
ityou/follow/browser/__init__.py
ityou/follow/browser/configure.zcml
ityou/follow/browser/controlpanel.py
ityou/follow/browser/follow.py
ityou/follow/browser/like.py
ityou/follow/browser/viewlets.py
ityou/follow/browser/images/ityou-esi-follow-icon.png
ityou/follow/browser/javascripts/follow-jq.js
ityou/follow/browser/templates/follow.pt
ityou/follow/browser/templates/like.pt
ityou/follow/locales/ityou.follow.pot
ityou/follow/locales/de/LC_MESSAGES/ityou.follow.po
ityou/follow/locales/en/LC_MESSAGES/ityou.follow.po
ityou/follow/profiles/default/browserlayer.xml
ityou/follow/profiles/default/controlpanel.xml
ityou/follow/profiles/default/jsregistry.xml
ityou/follow/profiles/default/metadata.xml
ityou/follow/profiles/default/registry.xml
ityou/follow/profiles/default/viewlets.xml